NetworkManager.py
python_networkmanager_legacy-2.2.1.dist-info/LICENSE
python_networkmanager_legacy-2.2.1.dist-info/METADATA
python_networkmanager_legacy-2.2.1.dist-info/WHEEL
python_networkmanager_legacy-2.2.1.dist-info/top_level.txt
python_networkmanager_legacy-2.2.1.dist-info/RECORD
