Metadata-Version: 2.1
Name: python-networkmanager-legacy
Version: 2.2.1
Summary: Easy communication with NetworkManager
Home-page: https://github.com/kt315ua/python-networkmanager-legacy
Author: Serhii Horelskyi
Classifier: Development Status :: 5 - Production/Stable
Classifier: Intended Audience :: Developers
Classifier: License :: OSI Approved :: zlib/libpng License
Classifier: Operating System :: POSIX :: Linux
Classifier: Programming Language :: Python
Classifier: Programming Language :: Python :: 3
Classifier: Topic :: System :: Networking
Requires-Python: >=3.6
License-File: LICENSE
Requires-Dist: dbus-python
Requires-Dist: six
